<level audio="">
    <LevelProperties>
        <camera_properties posx="0.000000" posy="0.000000" zoom_in_percent="0.850000" xOffset="0.000000" yOffset="-100.000000" xLag="15.000000" yLag="20.000000" followx="true" followy="false" />
        <level_bounds left="-1500.000000" right="1400.000000" top="500.000000" bottom="-700.000000" />
        <music file="" initial_delay="1.000000" length="96.000000" time_between="120.000000" />
        <weather_properties allow_weather="false" />
        <is_animation_preview value="false" />
    </LevelProperties>
    <Player id="1" level_edit_locked="false" updateable="true" always_update="true">
        <position depth_layer="kPlayer" y="216.000000" x="439.451904" rotation="0.000000" auto_rotate_value="0.000000" />
        <dimensions height="215.352036" width="181.393768" native="false" repeatX="false" repeatY="false" />
        <material value="maleninja" />
        <sine_wave_props active="false" x_offset="0.000000" y_offset="0.000000" amplitude="0.000000" rand_init_step="0" />
        <pos_audio_props enabled="false" file="" dim_x="0.000000" dim_y="0.000000" fade_dim_x="0.000000" fade_dim_y="0.000000" play_delay="0.100000" repeat="false" />
        <alpha value="1.000000" />
        <effect name="effectlighttexture" noiseintensity="0.000000" wobbleintensity="0.000000" pixelwobbleintensity="0.000000" pixelwobblespeedmod="0.000000" />
        <fade_when_player_occluded value="false" alphawhenoccluding="0.500000" alphawhennotoccluding="1.000000" />
        <texture filename="Media\subzero\still1.png" />
        <horizontalflip value="true" />
        <verticalflip value="true" />
        <isanimated value="true" />
        <animationfile value="XmlFiles\animation\player_anim_default.xml" />
        <foliage_sway_props bottom_left_intensity_x="0.000000" bottom_left_intensity_y="0.000000" bottom_right_intensity_x="0.000000" bottom_right_intensity_y="0.000000" top_left_intensity_x="0.000000" top_left_intensity_y="0.000000" top_right_intensity_x="0.000000" top_right_intensity_y="0.000000" time_multiplier="1.000000" />
        <resistance y="0.880000" x="0.800000" />
        <maxvelocity y="99999.000000" x="7.500000" />
        <applygravity value="true" />
        <collisionboxdimensions y="214.898743" x="128.959793" offsetX="0.000000" offsetY="0.000000" />
        <passive value="false" />
        <applydamage flag="false" amount="0.000000" />
        <can_be_damaged value="true" />
        <is_bouncy value="false" bounce_multiplier="0.000000" />
        <maxjumpspeed value="19" />
        <xaccelrate value="0.6" />
        <projectileoffsetx value="5" />
        <projectileoffsety value="25" />
    </Player>
    <Sprite id="2" level_edit_locked="false" updateable="true" always_update="false">
        <position depth_layer="kGround" y="-309.600037" x="-84.048073" rotation="0.170269" auto_rotate_value="0.000000" />
        <dimensions height="413.000000" width="2048.000000" native="true" repeatX="true" repeatY="false" />
        <material value="grassground" />
        <sine_wave_props active="false" x_offset="0.000000" y_offset="0.000000" amplitude="0.000000" rand_init_step="0" />
        <pos_audio_props enabled="false" file="" dim_x="0.000000" dim_y="0.000000" fade_dim_x="0.000000" fade_dim_y="0.000000" play_delay="0.100000" repeat="false" />
        <alpha value="1.000000" />
        <effect name="effectlighttexture" noiseintensity="0.000000" wobbleintensity="0.000000" pixelwobbleintensity="0.000000" pixelwobblespeedmod="0.000000" />
        <fade_when_player_occluded value="false" alphawhenoccluding="0.500000" alphawhennotoccluding="1.000000" />
        <texture filename="Media/levels/hot_spring/cave_floor_4.png" />
        <horizontalflip value="false" />
        <verticalflip value="true" />
        <isanimated value="false" />
        <foliage_sway_props bottom_left_intensity_x="0.000000" bottom_left_intensity_y="0.000000" bottom_right_intensity_x="0.000000" bottom_right_intensity_y="0.000000" top_left_intensity_x="0.000000" top_left_intensity_y="0.000000" top_right_intensity_x="0.000000" top_right_intensity_y="0.000000" time_multiplier="1.000000" />
    </Sprite>
    <Sprite id="3" level_edit_locked="true" updateable="true" always_update="false">
        <position depth_layer="kGround" y="-344.254395" x="254.849609" rotation="0.000000" auto_rotate_value="0.000000" />
        <dimensions height="545.000000" width="2048.000000" native="true" repeatX="false" repeatY="false" />
        <material value="grassground" />
        <sine_wave_props active="false" x_offset="0.000000" y_offset="0.000000" amplitude="0.000000" rand_init_step="0" />
        <pos_audio_props enabled="false" file="" dim_x="0.000000" dim_y="0.000000" fade_dim_x="0.000000" fade_dim_y="0.000000" play_delay="0.100000" repeat="false" />
        <alpha value="1.000000" />
        <effect name="effectlighttexture" noiseintensity="0.000000" wobbleintensity="0.000000" pixelwobbleintensity="0.000000" pixelwobblespeedmod="0.000000" />
        <fade_when_player_occluded value="false" alphawhenoccluding="0.500000" alphawhennotoccluding="1.000000" />
        <texture filename="Media/levels/hot_spring/water_pool.png" />
        <horizontalflip value="false" />
        <verticalflip value="false" />
        <isanimated value="false" />
        <foliage_sway_props bottom_left_intensity_x="0.000000" bottom_left_intensity_y="0.000000" bottom_right_intensity_x="0.000000" bottom_right_intensity_y="0.000000" top_left_intensity_x="0.000000" top_left_intensity_y="0.000000" top_right_intensity_x="0.000000" top_right_intensity_y="0.000000" time_multiplier="1.000000" />
    </Sprite>
    <Sprite id="4" level_edit_locked="false" updateable="true" always_update="false">
        <position depth_layer="kGroundFront" y="-504.000000" x="301.451904" rotation="0.000000" auto_rotate_value="0.000000" />
        <dimensions height="1278.843506" width="1368.678467" native="false" repeatX="false" repeatY="false" />
        <material value="grassground" />
        <sine_wave_props active="false" x_offset="0.000000" y_offset="0.000000" amplitude="0.000000" rand_init_step="0" />
        <pos_audio_props enabled="false" file="" dim_x="0.000000" dim_y="0.000000" fade_dim_x="0.000000" fade_dim_y="0.000000" play_delay="0.100000" repeat="false" />
        <alpha value="1.000000" />
        <effect name="effectfoliagesway" noiseintensity="0.000000" wobbleintensity="0.000000" pixelwobbleintensity="0.000000" pixelwobblespeedmod="0.000000" />
        <fade_when_player_occluded value="false" alphawhenoccluding="0.500000" alphawhennotoccluding="1.000000" />
        <texture filename="Media/levels/hot_spring/water_2.png" />
        <horizontalflip value="false" />
        <verticalflip value="false" />
        <isanimated value="false" />
        <foliage_sway_props bottom_left_intensity_x="0.000000" bottom_left_intensity_y="0.000000" bottom_right_intensity_x="0.000000" bottom_right_intensity_y="0.000000" top_left_intensity_x="0.000000" top_left_intensity_y="3.000000" top_right_intensity_x="0.000000" top_right_intensity_y="3.000000" time_multiplier="1.000000" />
    </Sprite>
    <Sprite id="5" level_edit_locked="false" updateable="true" always_update="false">
        <position depth_layer="kGround" y="-241.611359" x="1051.451904" rotation="0.210198" auto_rotate_value="0.000000" />
        <dimensions height="413.000000" width="2152.163330" native="false" repeatX="true" repeatY="false" />
        <material value="grassground" />
        <sine_wave_props active="false" x_offset="0.000000" y_offset="0.000000" amplitude="0.000000" rand_init_step="0" />
        <pos_audio_props enabled="false" file="" dim_x="0.000000" dim_y="0.000000" fade_dim_x="0.000000" fade_dim_y="0.000000" play_delay="0.100000" repeat="false" />
        <alpha value="1.000000" />
        <effect name="effectlighttexture" noiseintensity="0.000000" wobbleintensity="0.000000" pixelwobbleintensity="0.000000" pixelwobblespeedmod="0.000000" />
        <fade_when_player_occluded value="false" alphawhenoccluding="0.500000" alphawhennotoccluding="1.000000" />
        <texture filename="Media/levels/hot_spring/cave_floor_3.png" />
        <horizontalflip value="true" />
        <verticalflip value="true" />
        <isanimated value="false" />
        <foliage_sway_props bottom_left_intensity_x="0.000000" bottom_left_intensity_y="0.000000" bottom_right_intensity_x="0.000000" bottom_right_intensity_y="0.000000" top_left_intensity_x="0.000000" top_left_intensity_y="0.000000" top_right_intensity_x="0.000000" top_right_intensity_y="0.000000" time_multiplier="1.000000" />
    </Sprite>
    <Sprite id="6" level_edit_locked="false" updateable="true" always_update="false">
        <position depth_layer="kNearForeground" y="-445.910156" x="639.849609" rotation="0.000000" auto_rotate_value="0.000000" />
        <dimensions height="413.000000" width="13086.154297" native="false" repeatX="true" repeatY="false" />
        <material value="grassground" />
        <sine_wave_props active="false" x_offset="0.000000" y_offset="0.000000" amplitude="0.000000" rand_init_step="0" />
        <pos_audio_props enabled="false" file="" dim_x="0.000000" dim_y="0.000000" fade_dim_x="0.000000" fade_dim_y="0.000000" play_delay="0.100000" repeat="false" />
        <alpha value="1.000000" />
        <effect name="effectlighttexture" noiseintensity="0.000000" wobbleintensity="0.000000" pixelwobbleintensity="0.000000" pixelwobblespeedmod="0.000000" />
        <fade_when_player_occluded value="false" alphawhenoccluding="0.500000" alphawhennotoccluding="1.000000" />
        <texture filename="Media/levels/hot_spring/cave_ceiling_near.png" />
        <horizontalflip value="true" />
        <verticalflip value="true" />
        <isanimated value="false" />
        <foliage_sway_props bottom_left_intensity_x="0.000000" bottom_left_intensity_y="0.000000" bottom_right_intensity_x="0.000000" bottom_right_intensity_y="0.000000" top_left_intensity_x="0.000000" top_left_intensity_y="0.000000" top_right_intensity_x="0.000000" top_right_intensity_y="0.000000" time_multiplier="1.000000" />
    </Sprite>
    <Sprite id="7" level_edit_locked="false" updateable="true" always_update="false">
        <position depth_layer="kNearForeground" y="337.000000" x="1191.849609" rotation="0.000000" auto_rotate_value="0.000000" />
        <dimensions height="413.000000" width="13086.154297" native="false" repeatX="true" repeatY="false" />
        <material value="grassground" />
        <sine_wave_props active="false" x_offset="0.000000" y_offset="0.000000" amplitude="0.000000" rand_init_step="0" />
        <pos_audio_props enabled="false" file="" dim_x="0.000000" dim_y="0.000000" fade_dim_x="0.000000" fade_dim_y="0.000000" play_delay="0.100000" repeat="false" />
        <alpha value="1.000000" />
        <effect name="effectlighttexture" noiseintensity="0.000000" wobbleintensity="0.000000" pixelwobbleintensity="0.000000" pixelwobblespeedmod="0.000000" />
        <fade_when_player_occluded value="false" alphawhenoccluding="0.500000" alphawhennotoccluding="1.000000" />
        <texture filename="Media/levels/hot_spring/cave_ceiling_near.png" />
        <horizontalflip value="false" />
        <verticalflip value="false" />
        <isanimated value="false" />
        <foliage_sway_props bottom_left_intensity_x="0.000000" bottom_left_intensity_y="0.000000" bottom_right_intensity_x="0.000000" bottom_right_intensity_y="0.000000" top_left_intensity_x="0.000000" top_left_intensity_y="0.000000" top_right_intensity_x="0.000000" top_right_intensity_y="0.000000" time_multiplier="1.000000" />
    </Sprite>
    <Sprite id="8" level_edit_locked="false" updateable="true" always_update="false">
        <position depth_layer="kMiddleForeground" y="-495.000000" x="-110.150391" rotation="0.019629" auto_rotate_value="0.000000" />
        <dimensions height="334.913361" width="168.034729" native="false" repeatX="false" repeatY="false" />
        <material value="grassground" />
        <sine_wave_props active="false" x_offset="0.000000" y_offset="0.000000" amplitude="0.000000" rand_init_step="0" />
        <pos_audio_props enabled="false" file="" dim_x="0.000000" dim_y="0.000000" fade_dim_x="0.000000" fade_dim_y="0.000000" play_delay="0.100000" repeat="false" />
        <alpha value="0.950000" />
        <effect name="effectlighttexture" noiseintensity="0.000000" wobbleintensity="0.000000" pixelwobbleintensity="0.000000" pixelwobblespeedmod="0.000000" />
        <fade_when_player_occluded value="false" alphawhenoccluding="0.500000" alphawhennotoccluding="1.000000" />
        <texture filename="Media/levels/hot_spring/stalagmite_close.png" />
        <horizontalflip value="false" />
        <verticalflip value="false" />
        <isanimated value="false" />
        <foliage_sway_props bottom_left_intensity_x="0.000000" bottom_left_intensity_y="0.000000" bottom_right_intensity_x="0.000000" bottom_right_intensity_y="0.000000" top_left_intensity_x="0.000000" top_left_intensity_y="0.000000" top_right_intensity_x="0.000000" top_right_intensity_y="0.000000" time_multiplier="1.000000" />
    </Sprite>
    <Sprite id="9" level_edit_locked="false" updateable="true" always_update="false">
        <position depth_layer="kNearForeground" y="340.000000" x="-178.150391" rotation="0.019629" auto_rotate_value="0.000000" />
        <dimensions height="487.926758" width="244.805542" native="false" repeatX="false" repeatY="false" />
        <material value="grassground" />
        <sine_wave_props active="false" x_offset="0.000000" y_offset="0.000000" amplitude="0.000000" rand_init_step="0" />
        <pos_audio_props enabled="false" file="" dim_x="0.000000" dim_y="0.000000" fade_dim_x="0.000000" fade_dim_y="0.000000" play_delay="0.100000" repeat="false" />
        <alpha value="0.900000" />
        <effect name="effectlighttexture" noiseintensity="0.000000" wobbleintensity="0.000000" pixelwobbleintensity="0.000000" pixelwobblespeedmod="0.000000" />
        <fade_when_player_occluded value="false" alphawhenoccluding="0.500000" alphawhennotoccluding="1.000000" />
        <texture filename="Media/levels/hot_spring/stalagmite_close.png" />
        <horizontalflip value="false" />
        <verticalflip value="true" />
        <isanimated value="false" />
        <foliage_sway_props bottom_left_intensity_x="0.000000" bottom_left_intensity_y="0.000000" bottom_right_intensity_x="0.000000" bottom_right_intensity_y="0.000000" top_left_intensity_x="0.000000" top_left_intensity_y="0.000000" top_right_intensity_x="0.000000" top_right_intensity_y="0.000000" time_multiplier="1.000000" />
    </Sprite>
    <Sprite id="10" level_edit_locked="false" updateable="true" always_update="false">
        <position depth_layer="kMiddleForeground" y="-344.000000" x="-811.548096" rotation="0.019629" auto_rotate_value="0.000000" />
        <dimensions height="595.003296" width="298.528748" native="false" repeatX="false" repeatY="false" />
        <material value="grassground" />
        <sine_wave_props active="false" x_offset="0.000000" y_offset="0.000000" amplitude="0.000000" rand_init_step="0" />
        <pos_audio_props enabled="false" file="" dim_x="0.000000" dim_y="0.000000" fade_dim_x="0.000000" fade_dim_y="0.000000" play_delay="0.100000" repeat="false" />
        <alpha value="0.970000" />
        <effect name="effectlighttexture" noiseintensity="0.000000" wobbleintensity="0.000000" pixelwobbleintensity="0.000000" pixelwobblespeedmod="0.000000" />
        <fade_when_player_occluded value="false" alphawhenoccluding="0.500000" alphawhennotoccluding="1.000000" />
        <texture filename="Media/levels/hot_spring/stalagmite_close_2.png" />
        <horizontalflip value="false" />
        <verticalflip value="false" />
        <isanimated value="false" />
        <foliage_sway_props bottom_left_intensity_x="0.000000" bottom_left_intensity_y="0.000000" bottom_right_intensity_x="0.000000" bottom_right_intensity_y="0.000000" top_left_intensity_x="0.000000" top_left_intensity_y="0.000000" top_right_intensity_x="0.000000" top_right_intensity_y="0.000000" time_multiplier="1.000000" />
    </Sprite>
    <Sprite id="11" level_edit_locked="false" updateable="true" always_update="false">
        <position depth_layer="kNearForeground" y="337.000000" x="966.451904" rotation="0.019629" auto_rotate_value="0.000000" />
        <dimensions height="487.926758" width="244.805542" native="false" repeatX="false" repeatY="false" />
        <material value="grassground" />
        <sine_wave_props active="false" x_offset="0.000000" y_offset="0.000000" amplitude="0.000000" rand_init_step="0" />
        <pos_audio_props enabled="false" file="" dim_x="0.000000" dim_y="0.000000" fade_dim_x="0.000000" fade_dim_y="0.000000" play_delay="0.100000" repeat="false" />
        <alpha value="0.900000" />
        <effect name="effectlighttexture" noiseintensity="0.000000" wobbleintensity="0.000000" pixelwobbleintensity="0.000000" pixelwobblespeedmod="0.000000" />
        <fade_when_player_occluded value="false" alphawhenoccluding="0.500000" alphawhennotoccluding="1.000000" />
        <texture filename="Media/levels/hot_spring/stalagmite_close.png" />
        <horizontalflip value="false" />
        <verticalflip value="true" />
        <isanimated value="false" />
        <foliage_sway_props bottom_left_intensity_x="0.000000" bottom_left_intensity_y="0.000000" bottom_right_intensity_x="0.000000" bottom_right_intensity_y="0.000000" top_left_intensity_x="0.000000" top_left_intensity_y="0.000000" top_right_intensity_x="0.000000" top_right_intensity_y="0.000000" time_multiplier="1.000000" />
    </Sprite>
    <Sprite id="12" level_edit_locked="false" updateable="true" always_update="false">
        <position depth_layer="kNearForeground" y="-306.499969" x="-139.548096" rotation="0.019629" auto_rotate_value="0.000000" />
        <dimensions height="487.926758" width="244.805542" native="false" repeatX="false" repeatY="false" />
        <material value="grassground" />
        <sine_wave_props active="false" x_offset="0.000000" y_offset="0.000000" amplitude="0.000000" rand_init_step="0" />
        <pos_audio_props enabled="false" file="" dim_x="0.000000" dim_y="0.000000" fade_dim_x="0.000000" fade_dim_y="0.000000" play_delay="0.100000" repeat="false" />
        <alpha value="0.900000" />
        <effect name="effectlighttexture" noiseintensity="0.000000" wobbleintensity="0.000000" pixelwobbleintensity="0.000000" pixelwobblespeedmod="0.000000" />
        <fade_when_player_occluded value="false" alphawhenoccluding="0.500000" alphawhennotoccluding="1.000000" />
        <texture filename="Media/levels/hot_spring/stalagmite_close.png" />
        <horizontalflip value="false" />
        <verticalflip value="false" />
        <isanimated value="false" />
        <foliage_sway_props bottom_left_intensity_x="0.000000" bottom_left_intensity_y="0.000000" bottom_right_intensity_x="0.000000" bottom_right_intensity_y="0.000000" top_left_intensity_x="0.000000" top_left_intensity_y="0.000000" top_right_intensity_x="0.000000" top_right_intensity_y="0.000000" time_multiplier="1.000000" />
    </Sprite>
    <Sprite id="13" level_edit_locked="false" updateable="true" always_update="false">
        <position depth_layer="kMiddleForeground" y="-469.000000" x="772.849609" rotation="0.019629" auto_rotate_value="0.000000" />
        <dimensions height="334.913361" width="168.034729" native="false" repeatX="false" repeatY="false" />
        <material value="grassground" />
        <sine_wave_props active="false" x_offset="0.000000" y_offset="0.000000" amplitude="0.000000" rand_init_step="0" />
        <pos_audio_props enabled="false" file="" dim_x="0.000000" dim_y="0.000000" fade_dim_x="0.000000" fade_dim_y="0.000000" play_delay="0.100000" repeat="false" />
        <alpha value="0.950000" />
        <effect name="effectlighttexture" noiseintensity="0.000000" wobbleintensity="0.000000" pixelwobbleintensity="0.000000" pixelwobblespeedmod="0.000000" />
        <fade_when_player_occluded value="false" alphawhenoccluding="0.500000" alphawhennotoccluding="1.000000" />
        <texture filename="Media/levels/hot_spring/stalagmite_close.png" />
        <horizontalflip value="false" />
        <verticalflip value="false" />
        <isanimated value="false" />
        <foliage_sway_props bottom_left_intensity_x="0.000000" bottom_left_intensity_y="0.000000" bottom_right_intensity_x="0.000000" bottom_right_intensity_y="0.000000" top_left_intensity_x="0.000000" top_left_intensity_y="0.000000" top_right_intensity_x="0.000000" top_right_intensity_y="0.000000" time_multiplier="1.000000" />
    </Sprite>
    <Sprite id="14" level_edit_locked="false" updateable="true" always_update="false">
        <position depth_layer="kMiddleForeground" y="279.000000" x="530.849609" rotation="0.019629" auto_rotate_value="0.000000" />
        <dimensions height="334.913361" width="168.034729" native="false" repeatX="false" repeatY="false" />
        <material value="grassground" />
        <sine_wave_props active="false" x_offset="0.000000" y_offset="0.000000" amplitude="0.000000" rand_init_step="0" />
        <pos_audio_props enabled="false" file="" dim_x="0.000000" dim_y="0.000000" fade_dim_x="0.000000" fade_dim_y="0.000000" play_delay="0.100000" repeat="false" />
        <alpha value="0.950000" />
        <effect name="effectlighttexture" noiseintensity="0.000000" wobbleintensity="0.000000" pixelwobbleintensity="0.000000" pixelwobblespeedmod="0.000000" />
        <fade_when_player_occluded value="false" alphawhenoccluding="0.500000" alphawhennotoccluding="1.000000" />
        <texture filename="Media/levels/hot_spring/stalagmite_close.png" />
        <horizontalflip value="false" />
        <verticalflip value="true" />
        <isanimated value="false" />
        <foliage_sway_props bottom_left_intensity_x="0.000000" bottom_left_intensity_y="0.000000" bottom_right_intensity_x="0.000000" bottom_right_intensity_y="0.000000" top_left_intensity_x="0.000000" top_left_intensity_y="0.000000" top_right_intensity_x="0.000000" top_right_intensity_y="0.000000" time_multiplier="1.000000" />
    </Sprite>
    <ParticleSpray id="15" level_edit_locked="false" updateable="true" always_update="false">
        <position depth_layer="kGroundFront" y="-351.000000" x="193.451904" rotation="0.000000" auto_rotate_value="0.000000" spawn_spread_x="35.000000" spawn_spread_y="2.500000" />
        <dimensions height="317.648529" width="982.725159" />
        <material value="" />
        <sine_wave_props active="false" x_offset="0.000000" y_offset="0.000000" amplitude="0.000000" rand_init_step="0" />
        <pos_audio_props enabled="false" file="" dim_x="0.000000" dim_y="0.000000" fade_dim_x="0.000000" fade_dim_y="0.000000" play_delay="0.100000" repeat="false" />
        <alpha value="1.000000" />
        <effect name="effectlighttexture" />
        <fade_when_player_occluded value="false" alphawhenoccluding="0.500000" alphawhennotoccluding="1.000000" />
        <numparticles value="300.000000" />
        <texture filename="Media\Ambient\bubble.png" />
        <direction x="0.000000" y="1.000000" />
        <spread value="1.000000" />
        <speed min="1.500000" max="3.000000" />
        <livetime min="0.400000" max="0.600000" />
        <size min="1.000000" max="3.000000" scaleto="true" scaletovalue="8.000000" />
        <gravity value="0.000000" />
        <loop value="true" looptime="0.000000" />
        <brightness min="1.000000" max="1.000000" />
        <fade_time_percent out="0.250000" in="0.250000" />
    </ParticleSpray>
    <ParticleSpray id="16" level_edit_locked="false" updateable="true" always_update="false">
        <position depth_layer="kMiddleBackground" y="-215.000000" x="288.451904" rotation="0.000000" auto_rotate_value="0.000000" spawn_spread_x="85.000000" spawn_spread_y="6.000000" />
        <dimensions height="317.648529" width="982.725159" />
        <material value="" />
        <sine_wave_props active="false" x_offset="0.000000" y_offset="0.000000" amplitude="0.000000" rand_init_step="0" />
        <pos_audio_props enabled="false" file="" dim_x="0.000000" dim_y="0.000000" fade_dim_x="0.000000" fade_dim_y="0.000000" play_delay="0.100000" repeat="false" />
        <alpha value="1.000000" />
        <effect name="effectlighttexture" />
        <fade_when_player_occluded value="false" alphawhenoccluding="0.500000" alphawhennotoccluding="1.000000" />
        <numparticles value="200.000000" />
        <texture filename="Media\levels\hot_spring\fog_2.png" />
        <direction x="0.000000" y="1.000000" />
        <spread value="1.000000" />
        <speed min="0.100000" max="0.250000" />
        <livetime min="2.000000" max="5.500000" />
        <size min="45.000000" max="90.000000" scaleto="true" scaletovalue="4.500000" />
        <gravity value="0.000000" />
        <loop value="true" looptime="0.000000" />
        <brightness min="1.000000" max="1.000000" />
        <fade_time_percent out="0.250000" in="0.250000" />
    </ParticleSpray>
    <ParticleSpray id="17" level_edit_locked="false" updateable="true" always_update="false">
        <position depth_layer="kFarForeground" y="-485.099945" x="194.451904" rotation="0.000000" auto_rotate_value="0.000000" spawn_spread_x="60.000000" spawn_spread_y="6.000000" />
        <dimensions height="317.648529" width="982.725159" />
        <material value="" />
        <sine_wave_props active="false" x_offset="0.000000" y_offset="0.000000" amplitude="0.000000" rand_init_step="0" />
        <pos_audio_props enabled="false" file="" dim_x="0.000000" dim_y="0.000000" fade_dim_x="0.000000" fade_dim_y="0.000000" play_delay="0.100000" repeat="false" />
        <alpha value="1.000000" />
        <effect name="effectlighttexture" />
        <fade_when_player_occluded value="false" alphawhenoccluding="0.500000" alphawhennotoccluding="1.000000" />
        <numparticles value="50.000000" />
        <texture filename="Media\levels\hot_spring\fog_2.png" />
        <direction x="0.000000" y="1.000000" />
        <spread value="1.000000" />
        <speed min="0.050000" max="0.150000" />
        <livetime min="4.000000" max="6.500000" />
        <size min="50.000000" max="100.000000" scaleto="true" scaletovalue="10.000000" />
        <gravity value="0.000000" />
        <loop value="true" looptime="0.000000" />
        <brightness min="1.000000" max="1.000000" />
        <fade_time_percent out="0.250000" in="0.250000" />
    </ParticleSpray>
    <ParticleSpray id="18" level_edit_locked="false" updateable="true" always_update="false">
        <position depth_layer="kMiddleBackground" y="-87.000000" x="239.451904" rotation="0.000000" auto_rotate_value="0.000000" spawn_spread_x="120.000000" spawn_spread_y="30.000000" />
        <dimensions height="317.648529" width="982.725159" />
        <material value="" />
        <sine_wave_props active="false" x_offset="0.000000" y_offset="0.000000" amplitude="0.000000" rand_init_step="0" />
        <pos_audio_props enabled="false" file="" dim_x="0.000000" dim_y="0.000000" fade_dim_x="0.000000" fade_dim_y="0.000000" play_delay="0.100000" repeat="false" />
        <alpha value="1.000000" />
        <effect name="effectlighttexture" />
        <fade_when_player_occluded value="false" alphawhenoccluding="0.500000" alphawhennotoccluding="1.000000" />
        <numparticles value="100.000000" />
        <texture filename="Media\levels\hot_spring\fog_3.png" />
        <direction x="0.000000" y="1.000000" />
        <spread value="1.000000" />
        <speed min="0.020000" max="0.030000" />
        <livetime min="5.000000" max="10.000000" />
        <size min="150.000000" max="256.000000" scaleto="true" scaletovalue="4.000000" />
        <gravity value="0.000000" />
        <loop value="true" looptime="0.000000" />
        <brightness min="1.000000" max="1.000000" />
        <fade_time_percent out="0.250000" in="0.250000" />
    </ParticleSpray>
    <SolidLineStrip id="19" level_edit_locked="false" updateable="true" always_update="false">
        <position depth_layer="kSolidLines" y="-31.000000" x="-86.150391" rotation="0.000000" auto_rotate_value="0.000000" />
        <dimensions height="979.000000" width="1757.204590" native="false" repeatX="false" repeatY="false" />
        <material value="water" />
        <sine_wave_props active="false" x_offset="0.000000" y_offset="0.000000" amplitude="0.000000" rand_init_step="0" />
        <pos_audio_props enabled="false" file="" dim_x="0.000000" dim_y="0.000000" fade_dim_x="0.000000" fade_dim_y="0.000000" play_delay="0.100000" repeat="false" />
        <alpha value="1.000000" />
        <effect name="effectlighttexture" noiseintensity="0.000000" wobbleintensity="0.000000" pixelwobbleintensity="0.000000" pixelwobblespeedmod="0.000000" />
        <fade_when_player_occluded value="false" alphawhenoccluding="0.500000" alphawhennotoccluding="1.000000" />
        <texture filename="" />
        <horizontalflip value="false" />
        <verticalflip value="false" />
        <isanimated value="false" />
        <foliage_sway_props bottom_left_intensity_x="0.000000" bottom_left_intensity_y="0.000000" bottom_right_intensity_x="0.000000" bottom_right_intensity_y="0.000000" top_left_intensity_x="0.000000" top_left_intensity_y="0.000000" top_right_intensity_x="0.000000" top_right_intensity_y="0.000000" time_multiplier="1.000000" />
        <resistance y="1.000000" x="1.000000" />
        <maxvelocity y="0.000000" x="0.000000" />
        <applygravity value="false" />
        <collisionboxdimensions y="400.000000" x="1158.000000" offsetX="299.602295" offsetY="-289.500000" />
        <passive value="true" />
        <applydamage flag="false" amount="0.000000" />
        <can_be_damaged value="true" />
        <is_bouncy value="false" bounce_multiplier="1.300000" />
        <points x_0="-254.397705" y_0="-244.000000" x_1="93.602295" y_1="-329.000000" x_2="344.602295" y_2="-339.000000" x_3="625.602295" y_3="-321.000000" x_4="853.602295" y_4="-240.000000" num_points="5" />
        <edge_properties has_right_hard_edge="false" has_left_hard_edge="false" right_hard_edge_offset_x="0.000000" left_hard_edge_offset_x="0.000000" can_drop_down="false" />
    </SolidLineStrip>
    <SolidLineStrip id="20" level_edit_locked="false" updateable="true" always_update="false">
        <position depth_layer="kSolidLines" y="-280.000000" x="-453.150391" rotation="0.000000" auto_rotate_value="0.000000" />
        <dimensions height="938.000000" width="3002.795410" native="false" repeatX="false" repeatY="false" />
        <material value="caverock" />
        <sine_wave_props active="false" x_offset="0.000000" y_offset="0.000000" amplitude="0.000000" rand_init_step="0" />
        <pos_audio_props enabled="false" file="" dim_x="0.000000" dim_y="0.000000" fade_dim_x="0.000000" fade_dim_y="0.000000" play_delay="0.100000" repeat="false" />
        <alpha value="1.000000" />
        <effect name="effectlighttexture" noiseintensity="0.000000" wobbleintensity="0.000000" pixelwobbleintensity="0.000000" pixelwobblespeedmod="0.000000" />
        <fade_when_player_occluded value="false" alphawhenoccluding="0.500000" alphawhennotoccluding="1.000000" />
        <texture filename="" />
        <horizontalflip value="false" />
        <verticalflip value="false" />
        <isanimated value="false" />
        <foliage_sway_props bottom_left_intensity_x="0.000000" bottom_left_intensity_y="0.000000" bottom_right_intensity_x="0.000000" bottom_right_intensity_y="0.000000" top_left_intensity_x="0.000000" top_left_intensity_y="0.000000" top_right_intensity_x="0.000000" top_right_intensity_y="0.000000" time_multiplier="1.000000" />
        <resistance y="1.000000" x="1.000000" />
        <maxvelocity y="0.000000" x="0.000000" />
        <applygravity value="false" />
        <collisionboxdimensions y="515.000000" x="1644.000000" offsetX="-679.397705" offsetY="211.500000" />
        <passive value="true" />
        <applydamage flag="false" amount="0.000000" />
        <can_be_damaged value="true" />
        <is_bouncy value="false" bounce_multiplier="1.300000" />
        <points x_0="-1476.397705" y_0="419.000000" x_1="-610.397705" y_1="158.000000" x_2="-361.397705" y_2="116.000000" x_3="-59.397705" y_3="81.000000" x_4="117.602295" y_4="4.000000" num_points="5" />
        <edge_properties has_right_hard_edge="false" has_left_hard_edge="false" right_hard_edge_offset_x="0.000000" left_hard_edge_offset_x="0.000000" can_drop_down="true" />
    </SolidLineStrip>
    <SolidLineStrip id="21" level_edit_locked="false" updateable="true" always_update="false">
        <position depth_layer="kSolidLines" y="-120.000000" x="986.849609" rotation="0.000000" auto_rotate_value="0.000000" />
        <dimensions height="621.000000" width="2078.000000" native="false" repeatX="false" repeatY="false" />
        <material value="caverock" />
        <sine_wave_props active="false" x_offset="0.000000" y_offset="0.000000" amplitude="0.000000" rand_init_step="0" />
        <pos_audio_props enabled="false" file="" dim_x="0.000000" dim_y="0.000000" fade_dim_x="0.000000" fade_dim_y="0.000000" play_delay="0.100000" repeat="false" />
        <alpha value="1.000000" />
        <effect name="effectlighttexture" noiseintensity="0.000000" wobbleintensity="0.000000" pixelwobbleintensity="0.000000" pixelwobblespeedmod="0.000000" />
        <fade_when_player_occluded value="false" alphawhenoccluding="0.500000" alphawhennotoccluding="1.000000" />
        <texture filename="" />
        <horizontalflip value="false" />
        <verticalflip value="false" />
        <isanimated value="false" />
        <foliage_sway_props bottom_left_intensity_x="0.000000" bottom_left_intensity_y="0.000000" bottom_right_intensity_x="0.000000" bottom_right_intensity_y="0.000000" top_left_intensity_x="0.000000" top_left_intensity_y="0.000000" top_right_intensity_x="0.000000" top_right_intensity_y="0.000000" time_multiplier="1.000000" />
        <resistance y="1.000000" x="1.000000" />
        <maxvelocity y="0.000000" x="0.000000" />
        <applygravity value="false" />
        <collisionboxdimensions y="400.000000" x="1293.397705" offsetX="392.301147" offsetY="-110.500000" />
        <passive value="true" />
        <applydamage flag="false" amount="0.000000" />
        <can_be_damaged value="true" />
        <is_bouncy value="false" bounce_multiplier="1.300000" />
        <points x_0="-229.397705" y_0="-152.000000" x_1="83.602295" y_1="-135.000000" x_2="339.602295" y_2="-81.000000" x_3="1014.000000" y_3="-69.000000" num_points="4" />
        <edge_properties has_right_hard_edge="true" has_left_hard_edge="false" right_hard_edge_offset_x="20.000000" left_hard_edge_offset_x="0.000000" can_drop_down="false" />
    </SolidLineStrip>
    <Sprite id="22" level_edit_locked="false" updateable="true" always_update="false">
        <position depth_layer="kFarBackground" y="-180.000000" x="-124.548073" rotation="0.000000" auto_rotate_value="0.000000" />
        <dimensions height="156.623169" width="776.668762" native="false" repeatX="false" repeatY="false" />
        <material value="grassground" />
        <sine_wave_props active="false" x_offset="0.000000" y_offset="0.000000" amplitude="0.000000" rand_init_step="0" />
        <pos_audio_props enabled="false" file="" dim_x="0.000000" dim_y="0.000000" fade_dim_x="0.000000" fade_dim_y="0.000000" play_delay="0.100000" repeat="false" />
        <alpha value="0.750000" />
        <effect name="effectlighttexture" noiseintensity="0.000000" wobbleintensity="0.000000" pixelwobbleintensity="0.000000" pixelwobblespeedmod="0.000000" />
        <fade_when_player_occluded value="false" alphawhenoccluding="0.500000" alphawhennotoccluding="1.000000" />
        <texture filename="Media/levels/hot_spring/cave_floor_3.png" />
        <horizontalflip value="true" />
        <verticalflip value="true" />
        <isanimated value="false" />
        <foliage_sway_props bottom_left_intensity_x="0.000000" bottom_left_intensity_y="0.000000" bottom_right_intensity_x="0.000000" bottom_right_intensity_y="0.000000" top_left_intensity_x="0.000000" top_left_intensity_y="0.000000" top_right_intensity_x="0.000000" top_right_intensity_y="0.000000" time_multiplier="1.000000" />
    </Sprite>
    <Sprite id="23" level_edit_locked="false" updateable="true" always_update="false">
        <position depth_layer="kFarBackground" y="-243.000000" x="1989.849609" rotation="0.000000" auto_rotate_value="0.000000" />
        <dimensions height="156.623169" width="776.668762" native="false" repeatX="false" repeatY="false" />
        <material value="grassground" />
        <sine_wave_props active="false" x_offset="0.000000" y_offset="0.000000" amplitude="0.000000" rand_init_step="0" />
        <pos_audio_props enabled="false" file="" dim_x="0.000000" dim_y="0.000000" fade_dim_x="0.000000" fade_dim_y="0.000000" play_delay="0.100000" repeat="false" />
        <alpha value="0.750000" />
        <effect name="effectlighttexture" noiseintensity="0.000000" wobbleintensity="0.000000" pixelwobbleintensity="0.000000" pixelwobblespeedmod="0.000000" />
        <fade_when_player_occluded value="false" alphawhenoccluding="0.500000" alphawhennotoccluding="1.000000" />
        <texture filename="Media/levels/hot_spring/cave_floor_3.png" />
        <horizontalflip value="false" />
        <verticalflip value="true" />
        <isanimated value="false" />
        <foliage_sway_props bottom_left_intensity_x="0.000000" bottom_left_intensity_y="0.000000" bottom_right_intensity_x="0.000000" bottom_right_intensity_y="0.000000" top_left_intensity_x="0.000000" top_left_intensity_y="0.000000" top_right_intensity_x="0.000000" top_right_intensity_y="0.000000" time_multiplier="1.000000" />
    </Sprite>
    <Sprite id="24" level_edit_locked="false" updateable="true" always_update="false">
        <position depth_layer="kNearBackground" y="-183.000000" x="1416.849609" rotation="-0.237837" auto_rotate_value="0.000000" />
        <dimensions height="260.213135" width="1290.354614" native="false" repeatX="false" repeatY="false" />
        <material value="grassground" />
        <sine_wave_props active="false" x_offset="0.000000" y_offset="0.000000" amplitude="0.000000" rand_init_step="0" />
        <pos_audio_props enabled="false" file="" dim_x="0.000000" dim_y="0.000000" fade_dim_x="0.000000" fade_dim_y="0.000000" play_delay="0.100000" repeat="false" />
        <alpha value="1.000000" />
        <effect name="effectlighttexture" noiseintensity="0.000000" wobbleintensity="0.000000" pixelwobbleintensity="0.000000" pixelwobblespeedmod="0.000000" />
        <fade_when_player_occluded value="false" alphawhenoccluding="0.500000" alphawhennotoccluding="1.000000" />
        <texture filename="Media/levels/hot_spring/cave_floor_3.png" />
        <horizontalflip value="false" />
        <verticalflip value="true" />
        <isanimated value="false" />
        <foliage_sway_props bottom_left_intensity_x="0.000000" bottom_left_intensity_y="0.000000" bottom_right_intensity_x="0.000000" bottom_right_intensity_y="0.000000" top_left_intensity_x="0.000000" top_left_intensity_y="0.000000" top_right_intensity_x="0.000000" top_right_intensity_y="0.000000" time_multiplier="1.000000" />
    </Sprite>
    <ScrollingSprite id="25" level_edit_locked="false" updateable="true" always_update="false">
        <position depth_layer="kFarBackground" y="120.000000" x="-1467.150391" rotation="0.000000" auto_rotate_value="0.000000" />
        <dimensions height="2697.064941" width="4156.407227" native="false" repeatX="false" repeatY="false" />
        <material value="grassground" />
        <sine_wave_props active="false" x_offset="0.000000" y_offset="0.000000" amplitude="0.000000" rand_init_step="0" />
        <pos_audio_props enabled="false" file="" dim_x="0.000000" dim_y="0.000000" fade_dim_x="0.000000" fade_dim_y="0.000000" play_delay="0.100000" repeat="false" />
        <alpha value="0.300000" />
        <effect name="effectpixelwobble" noiseintensity="0.000000" wobbleintensity="0.000000" pixelwobbleintensity="0.050000" pixelwobblespeedmod="0.300000" />
        <fade_when_player_occluded value="false" alphawhenoccluding="0.500000" alphawhennotoccluding="1.000000" />
        <texture filename="Media\fog.png" />
        <horizontalflip value="false" />
        <verticalflip value="false" />
        <isanimated value="false" />
        <foliage_sway_props bottom_left_intensity_x="0.000000" bottom_left_intensity_y="0.000000" bottom_right_intensity_x="0.000000" bottom_right_intensity_y="0.000000" top_left_intensity_x="0.000000" top_left_intensity_y="0.000000" top_right_intensity_x="0.000000" top_right_intensity_y="0.000000" time_multiplier="1.000000" />
        <scroll_properties StartLerpX="-1467.150391" StartLerpY="120.000000" LerpDistanceX="1000.000000" LerpDistanceY="0.000000" LerpTime="20.000000" FadeInTime="5.000000" FadeOutTime="5.000000" />
    </ScrollingSprite>
    <ScrollingSprite id="26" level_edit_locked="false" updateable="true" always_update="false">
        <position depth_layer="kFarBackground" y="250.000000" x="2411.849609" rotation="0.000000" auto_rotate_value="0.000000" />
        <dimensions height="2316.791748" width="3570.373535" native="false" repeatX="false" repeatY="false" />
        <material value="grassground" />
        <sine_wave_props active="false" x_offset="0.000000" y_offset="0.000000" amplitude="0.000000" rand_init_step="0" />
        <pos_audio_props enabled="false" file="" dim_x="0.000000" dim_y="0.000000" fade_dim_x="0.000000" fade_dim_y="0.000000" play_delay="0.100000" repeat="false" />
        <alpha value="0.400000" />
        <effect name="effectpixelwobble" noiseintensity="0.000000" wobbleintensity="0.000000" pixelwobbleintensity="0.050000" pixelwobblespeedmod="0.300000" />
        <fade_when_player_occluded value="false" alphawhenoccluding="0.500000" alphawhennotoccluding="1.000000" />
        <texture filename="Media\fog.png" />
        <horizontalflip value="true" />
        <verticalflip value="false" />
        <isanimated value="false" />
        <foliage_sway_props bottom_left_intensity_x="0.000000" bottom_left_intensity_y="0.000000" bottom_right_intensity_x="0.000000" bottom_right_intensity_y="0.000000" top_left_intensity_x="0.000000" top_left_intensity_y="0.000000" top_right_intensity_x="0.000000" top_right_intensity_y="0.000000" time_multiplier="1.000000" />
        <scroll_properties StartLerpX="2411.849609" StartLerpY="250.000000" LerpDistanceX="-800.000000" LerpDistanceY="0.000000" LerpTime="20.000000" FadeInTime="5.000000" FadeOutTime="5.000000" />
    </ScrollingSprite>
    <Sprite id="27" level_edit_locked="false" updateable="true" always_update="false">
        <position depth_layer="kMiddleForeground" y="314.000000" x="357.849609" rotation="0.000000" auto_rotate_value="0.000000" />
        <dimensions height="413.000000" width="13086.154297" native="false" repeatX="true" repeatY="false" />
        <material value="grassground" />
        <sine_wave_props active="false" x_offset="0.000000" y_offset="0.000000" amplitude="0.000000" rand_init_step="0" />
        <pos_audio_props enabled="false" file="" dim_x="0.000000" dim_y="0.000000" fade_dim_x="0.000000" fade_dim_y="0.000000" play_delay="0.100000" repeat="false" />
        <alpha value="0.700000" />
        <effect name="effectlighttexture" noiseintensity="0.000000" wobbleintensity="0.000000" pixelwobbleintensity="0.000000" pixelwobblespeedmod="0.000000" />
        <fade_when_player_occluded value="false" alphawhenoccluding="0.500000" alphawhennotoccluding="1.000000" />
        <texture filename="Media/levels/hot_spring/cave_ceiling_near.png" />
        <horizontalflip value="false" />
        <verticalflip value="false" />
        <isanimated value="false" />
        <foliage_sway_props bottom_left_intensity_x="0.000000" bottom_left_intensity_y="0.000000" bottom_right_intensity_x="0.000000" bottom_right_intensity_y="0.000000" top_left_intensity_x="0.000000" top_left_intensity_y="0.000000" top_right_intensity_x="0.000000" top_right_intensity_y="0.000000" time_multiplier="1.000000" />
    </Sprite>
    <Sprite id="28" level_edit_locked="false" updateable="true" always_update="false">
        <position depth_layer="kMiddleForeground" y="377.000000" x="44.849609" rotation="0.019629" auto_rotate_value="0.000000" />
        <dimensions height="334.913361" width="168.034729" native="false" repeatX="false" repeatY="false" />
        <material value="grassground" />
        <sine_wave_props active="false" x_offset="0.000000" y_offset="0.000000" amplitude="0.000000" rand_init_step="0" />
        <pos_audio_props enabled="false" file="" dim_x="0.000000" dim_y="0.000000" fade_dim_x="0.000000" fade_dim_y="0.000000" play_delay="0.100000" repeat="false" />
        <alpha value="0.950000" />
        <effect name="effectlighttexture" noiseintensity="0.000000" wobbleintensity="0.000000" pixelwobbleintensity="0.000000" pixelwobblespeedmod="0.000000" />
        <fade_when_player_occluded value="false" alphawhenoccluding="0.500000" alphawhennotoccluding="1.000000" />
        <texture filename="Media/levels/hot_spring/stalagmite_close.png" />
        <horizontalflip value="false" />
        <verticalflip value="true" />
        <isanimated value="false" />
        <foliage_sway_props bottom_left_intensity_x="0.000000" bottom_left_intensity_y="0.000000" bottom_right_intensity_x="0.000000" bottom_right_intensity_y="0.000000" top_left_intensity_x="0.000000" top_left_intensity_y="0.000000" top_right_intensity_x="0.000000" top_right_intensity_y="0.000000" time_multiplier="1.000000" />
    </Sprite>
    <Sprite id="29" level_edit_locked="false" updateable="true" always_update="false">
        <position depth_layer="kMiddleForeground" y="351.000000" x="1629.849609" rotation="0.019629" auto_rotate_value="0.000000" />
        <dimensions height="334.913361" width="168.034729" native="false" repeatX="false" repeatY="false" />
        <material value="grassground" />
        <sine_wave_props active="false" x_offset="0.000000" y_offset="0.000000" amplitude="0.000000" rand_init_step="0" />
        <pos_audio_props enabled="false" file="" dim_x="0.000000" dim_y="0.000000" fade_dim_x="0.000000" fade_dim_y="0.000000" play_delay="0.100000" repeat="false" />
        <alpha value="0.950000" />
        <effect name="effectlighttexture" noiseintensity="0.000000" wobbleintensity="0.000000" pixelwobbleintensity="0.000000" pixelwobblespeedmod="0.000000" />
        <fade_when_player_occluded value="false" alphawhenoccluding="0.500000" alphawhennotoccluding="1.000000" />
        <texture filename="Media/levels/hot_spring/stalagmite_close.png" />
        <horizontalflip value="false" />
        <verticalflip value="true" />
        <isanimated value="false" />
        <foliage_sway_props bottom_left_intensity_x="0.000000" bottom_left_intensity_y="0.000000" bottom_right_intensity_x="0.000000" bottom_right_intensity_y="0.000000" top_left_intensity_x="0.000000" top_left_intensity_y="0.000000" top_right_intensity_x="0.000000" top_right_intensity_y="0.000000" time_multiplier="1.000000" />
    </Sprite>
    <Sprite id="30" level_edit_locked="false" updateable="true" always_update="false">
        <position depth_layer="kGround" y="245.000000" x="66.451904" rotation="0.290028" auto_rotate_value="0.000000" />
        <dimensions height="1303.984009" width="654.242615" native="false" repeatX="false" repeatY="false" />
        <material value="grassground" />
        <sine_wave_props active="false" x_offset="0.000000" y_offset="0.000000" amplitude="0.000000" rand_init_step="0" />
        <pos_audio_props enabled="false" file="" dim_x="0.000000" dim_y="0.000000" fade_dim_x="0.000000" fade_dim_y="0.000000" play_delay="0.100000" repeat="false" />
        <alpha value="0.750000" />
        <effect name="effectlighttexture" noiseintensity="0.000000" wobbleintensity="0.000000" pixelwobbleintensity="0.000000" pixelwobblespeedmod="0.000000" />
        <fade_when_player_occluded value="false" alphawhenoccluding="0.500000" alphawhennotoccluding="1.000000" />
        <texture filename="Media/sun_shaft_2.png" />
        <horizontalflip value="false" />
        <verticalflip value="false" />
        <isanimated value="false" />
        <foliage_sway_props bottom_left_intensity_x="0.000000" bottom_left_intensity_y="0.000000" bottom_right_intensity_x="0.000000" bottom_right_intensity_y="0.000000" top_left_intensity_x="0.000000" top_left_intensity_y="0.000000" top_right_intensity_x="0.000000" top_right_intensity_y="0.000000" time_multiplier="1.000000" />
    </Sprite>
    <ParticleSpray id="31" level_edit_locked="false" updateable="true" always_update="false">
        <position depth_layer="kNearBackground" y="271.000000" x="52.451904" rotation="0.000000" auto_rotate_value="0.000000" spawn_spread_x="17.000000" spawn_spread_y="15.000000" />
        <dimensions height="309.712708" width="400.000000" />
        <material value="" />
        <sine_wave_props active="false" x_offset="0.000000" y_offset="0.000000" amplitude="0.000000" rand_init_step="0" />
        <pos_audio_props enabled="false" file="" dim_x="0.000000" dim_y="0.000000" fade_dim_x="0.000000" fade_dim_y="0.000000" play_delay="0.100000" repeat="false" />
        <alpha value="1.000000" />
        <effect name="effectlighttexture" />
        <fade_when_player_occluded value="false" alphawhenoccluding="0.500000" alphawhennotoccluding="1.000000" />
        <numparticles value="75.000000" />
        <texture filename="Media\Ambient\dust_mote.png" />
        <direction x="0.200000" y="-0.800000" />
        <spread value="1.000000" />
        <speed min="0.150000" max="0.500000" />
        <livetime min="1.500000" max="2.500000" />
        <size min="5.000000" max="20.000000" scaleto="true" scaletovalue="2.000000" />
        <gravity value="0.000000" />
        <loop value="true" looptime="0.000000" />
        <brightness min="1.000000" max="1.000000" />
        <fade_time_percent out="0.250000" in="0.250000" />
    </ParticleSpray>
    <Butterfly id="32" level_edit_locked="false" updateable="true" always_update="true">
        <position depth_layer="kGround" y="29.000000" x="47.451904" rotation="0.000000" auto_rotate_value="0.000000" />
        <dimensions height="62.442642" width="62.442642" native="false" repeatX="false" repeatY="false" />
        <material value="rabbit" />
        <sine_wave_props active="false" x_offset="0.000000" y_offset="0.000000" amplitude="0.000000" rand_init_step="0" />
        <pos_audio_props enabled="false" file="" dim_x="0.000000" dim_y="0.000000" fade_dim_x="0.000000" fade_dim_y="0.000000" play_delay="0.100000" repeat="false" />
        <alpha value="1.000000" />
        <effect name="effectlighttexture" noiseintensity="0.000000" wobbleintensity="0.000000" pixelwobbleintensity="0.000000" pixelwobblespeedmod="0.000000" />
        <fade_when_player_occluded value="false" alphawhenoccluding="0.500000" alphawhennotoccluding="1.000000" />
        <texture filename="Media\subzero\still1.png" />
        <horizontalflip value="true" />
        <verticalflip value="false" />
        <isanimated value="true" />
        <animationfile value="XmlFiles\butterfly_anim.xml" />
        <foliage_sway_props bottom_left_intensity_x="0.000000" bottom_left_intensity_y="0.000000" bottom_right_intensity_x="0.000000" bottom_right_intensity_y="0.000000" top_left_intensity_x="0.000000" top_left_intensity_y="0.000000" top_right_intensity_x="0.000000" top_right_intensity_y="0.000000" time_multiplier="1.000000" />
        <resistance y="6.000000" x="0.990000" />
        <maxvelocity y="5.000000" x="0.500000" />
        <applygravity value="true" />
        <collisionboxdimensions y="26.509336" x="26.509336" offsetX="0.000000" offsetY="0.000000" />
        <passive value="true" />
        <applydamage flag="false" amount="0.000000" />
        <can_be_damaged value="true" />
        <is_bouncy value="false" bounce_multiplier="1.300000" />
        <maxjumpspeed value="25" />
        <xaccelrate value="0.5" />
        <projectileoffsetx value="15" />
        <projectileoffsety value="20" />
    </Butterfly>
    <Butterfly id="33" level_edit_locked="false" updateable="true" always_update="true">
        <position depth_layer="kNearBackground" y="42.000000" x="154.451904" rotation="0.000000" auto_rotate_value="0.000000" />
        <dimensions height="46.939617" width="46.939617" native="false" repeatX="false" repeatY="false" />
        <material value="rabbit" />
        <sine_wave_props active="false" x_offset="0.000000" y_offset="0.000000" amplitude="0.000000" rand_init_step="0" />
        <pos_audio_props enabled="false" file="" dim_x="0.000000" dim_y="0.000000" fade_dim_x="0.000000" fade_dim_y="0.000000" play_delay="0.100000" repeat="false" />
        <alpha value="1.000000" />
        <effect name="effectlighttexture" noiseintensity="0.000000" wobbleintensity="0.000000" pixelwobbleintensity="0.000000" pixelwobblespeedmod="0.000000" />
        <fade_when_player_occluded value="false" alphawhenoccluding="0.500000" alphawhennotoccluding="1.000000" />
        <texture filename="Media\subzero\still1.png" />
        <horizontalflip value="true" />
        <verticalflip value="false" />
        <isanimated value="true" />
        <animationfile value="XmlFiles\butterfly_anim.xml" />
        <foliage_sway_props bottom_left_intensity_x="0.000000" bottom_left_intensity_y="0.000000" bottom_right_intensity_x="0.000000" bottom_right_intensity_y="0.000000" top_left_intensity_x="0.000000" top_left_intensity_y="0.000000" top_right_intensity_x="0.000000" top_right_intensity_y="0.000000" time_multiplier="1.000000" />
        <resistance y="6.000000" x="0.990000" />
        <maxvelocity y="5.000000" x="0.500000" />
        <applygravity value="true" />
        <collisionboxdimensions y="26.509336" x="26.509336" offsetX="0.000000" offsetY="0.000000" />
        <passive value="true" />
        <applydamage flag="false" amount="0.000000" />
        <can_be_damaged value="true" />
        <is_bouncy value="false" bounce_multiplier="1.300000" />
        <maxjumpspeed value="25" />
        <xaccelrate value="0.5" />
        <projectileoffsetx value="15" />
        <projectileoffsety value="20" />
    </Butterfly>
    <Sprite id="34" level_edit_locked="false" updateable="true" always_update="false">
        <position depth_layer="kFarForeground" y="-205.000000" x="-1217.851196" rotation="-0.119797" auto_rotate_value="0.000000" />
        <dimensions height="1500.000000" width="700.000000" native="false" repeatX="false" repeatY="false" />
        <material value="grassground" />
        <sine_wave_props active="false" x_offset="0.000000" y_offset="0.000000" amplitude="0.000000" rand_init_step="0" />
        <pos_audio_props enabled="false" file="" dim_x="0.000000" dim_y="0.000000" fade_dim_x="0.000000" fade_dim_y="0.000000" play_delay="0.100000" repeat="false" />
        <alpha value="1.000000" />
        <effect name="effectlighttexture" noiseintensity="0.000000" wobbleintensity="0.000000" pixelwobbleintensity="0.000000" pixelwobblespeedmod="0.000000" />
        <fade_when_player_occluded value="false" alphawhenoccluding="0.500000" alphawhennotoccluding="1.000000" />
        <texture filename="Media/edge_fade_left.png" />
        <horizontalflip value="false" />
        <verticalflip value="false" />
        <isanimated value="false" />
        <foliage_sway_props bottom_left_intensity_x="0.000000" bottom_left_intensity_y="0.000000" bottom_right_intensity_x="0.000000" bottom_right_intensity_y="0.000000" top_left_intensity_x="0.000000" top_left_intensity_y="0.000000" top_right_intensity_x="0.000000" top_right_intensity_y="0.000000" time_multiplier="1.000000" />
    </Sprite>
    <SolidMovingSprite id="35" level_edit_locked="true" updateable="true" always_update="false">
        <position depth_layer="kGround" y="6.000000" x="-1794.150391" rotation="0.000000" auto_rotate_value="0.000000" />
        <dimensions height="64.000000" width="64.000000" native="true" repeatX="false" repeatY="false" />
        <material value="caverock" />
        <sine_wave_props active="false" x_offset="0.000000" y_offset="0.000000" amplitude="0.000000" rand_init_step="0" />
        <pos_audio_props enabled="false" file="" dim_x="0.000000" dim_y="0.000000" fade_dim_x="0.000000" fade_dim_y="0.000000" play_delay="0.100000" repeat="false" />
        <alpha value="0.000000" />
        <effect name="effectlighttexture" noiseintensity="0.000000" wobbleintensity="0.000000" pixelwobbleintensity="0.000000" pixelwobblespeedmod="0.000000" />
        <fade_when_player_occluded value="false" alphawhenoccluding="0.500000" alphawhennotoccluding="1.000000" />
        <texture filename="Media\Ambient\dust_mote.png" />
        <horizontalflip value="false" />
        <verticalflip value="false" />
        <isanimated value="false" />
        <foliage_sway_props bottom_left_intensity_x="0.000000" bottom_left_intensity_y="0.000000" bottom_right_intensity_x="0.000000" bottom_right_intensity_y="0.000000" top_left_intensity_x="0.000000" top_left_intensity_y="0.000000" top_right_intensity_x="0.000000" top_right_intensity_y="0.000000" time_multiplier="1.000000" />
        <resistance y="2.000000" x="0.950000" />
        <maxvelocity y="99999.000000" x="10.000000" />
        <applygravity value="false" />
        <collisionboxdimensions y="4000.000000" x="658.244568" offsetX="0.000000" offsetY="0.000000" />
        <passive value="true" />
        <applydamage flag="false" amount="0.000000" />
        <can_be_damaged value="false" />
        <is_bouncy value="true" bounce_multiplier="1.100000" />
    </SolidMovingSprite>
    <SolidMovingSprite id="36" level_edit_locked="true" updateable="true" always_update="false">
        <position depth_layer="kGround" y="115.000000" x="1835.849609" rotation="0.000000" auto_rotate_value="0.000000" />
        <dimensions height="64.000000" width="64.000000" native="true" repeatX="false" repeatY="false" />
        <material value="caverock" />
        <sine_wave_props active="false" x_offset="0.000000" y_offset="0.000000" amplitude="0.000000" rand_init_step="0" />
        <pos_audio_props enabled="false" file="" dim_x="0.000000" dim_y="0.000000" fade_dim_x="0.000000" fade_dim_y="0.000000" play_delay="0.100000" repeat="false" />
        <alpha value="0.000000" />
        <effect name="effectlighttexture" noiseintensity="0.000000" wobbleintensity="0.000000" pixelwobbleintensity="0.000000" pixelwobblespeedmod="0.000000" />
        <fade_when_player_occluded value="false" alphawhenoccluding="0.500000" alphawhennotoccluding="1.000000" />
        <texture filename="Media\Ambient\dust_mote.png" />
        <horizontalflip value="false" />
        <verticalflip value="false" />
        <isanimated value="false" />
        <foliage_sway_props bottom_left_intensity_x="0.000000" bottom_left_intensity_y="0.000000" bottom_right_intensity_x="0.000000" bottom_right_intensity_y="0.000000" top_left_intensity_x="0.000000" top_left_intensity_y="0.000000" top_right_intensity_x="0.000000" top_right_intensity_y="0.000000" time_multiplier="1.000000" />
        <resistance y="2.000000" x="0.950000" />
        <maxvelocity y="99999.000000" x="10.000000" />
        <applygravity value="false" />
        <collisionboxdimensions y="4000.000000" x="658.244568" offsetX="0.000000" offsetY="0.000000" />
        <passive value="true" />
        <applydamage flag="false" amount="0.000000" />
        <can_be_damaged value="false" />
        <is_bouncy value="true" bounce_multiplier="1.100000" />
    </SolidMovingSprite>
    <Sprite id="37" level_edit_locked="false" updateable="true" always_update="false">
        <position depth_layer="kGround" y="-145.000000" x="1086.452148" rotation="-1.429937" auto_rotate_value="0.000000" />
        <dimensions height="555.563721" width="416.672760" native="false" repeatX="false" repeatY="false" />
        <material value="grassground" />
        <sine_wave_props active="false" x_offset="0.000000" y_offset="0.000000" amplitude="0.000000" rand_init_step="0" />
        <pos_audio_props enabled="false" file="" dim_x="0.000000" dim_y="0.000000" fade_dim_x="0.000000" fade_dim_y="0.000000" play_delay="0.100000" repeat="false" />
        <alpha value="1.000000" />
        <effect name="effectlighttexture" noiseintensity="0.000000" wobbleintensity="0.000000" pixelwobbleintensity="0.000000" pixelwobblespeedmod="0.000000" />
        <fade_when_player_occluded value="false" alphawhenoccluding="0.500000" alphawhennotoccluding="1.000000" />
        <texture filename="Media/sun_shaft_2.png" />
        <horizontalflip value="false" />
        <verticalflip value="false" />
        <isanimated value="false" />
        <foliage_sway_props bottom_left_intensity_x="0.000000" bottom_left_intensity_y="0.000000" bottom_right_intensity_x="0.000000" bottom_right_intensity_y="0.000000" top_left_intensity_x="0.000000" top_left_intensity_y="0.000000" top_right_intensity_x="0.000000" top_right_intensity_y="0.000000" time_multiplier="1.000000" />
    </Sprite>
    <Sprite id="38" level_edit_locked="false" updateable="true" always_update="false">
        <position depth_layer="kFarBackground" y="-164.000000" x="173.451904" rotation="0.000000" auto_rotate_value="0.000000" />
        <dimensions height="1564.628784" width="2347.859863" native="false" repeatX="false" repeatY="false" />
        <material value="grassground" />
        <sine_wave_props active="false" x_offset="0.000000" y_offset="0.000000" amplitude="0.000000" rand_init_step="0" />
        <pos_audio_props enabled="false" file="" dim_x="0.000000" dim_y="0.000000" fade_dim_x="0.000000" fade_dim_y="0.000000" play_delay="0.100000" repeat="false" />
        <alpha value="0.550000" />
        <effect name="effectlighttexture" noiseintensity="0.000000" wobbleintensity="0.000000" pixelwobbleintensity="0.000000" pixelwobblespeedmod="0.000000" />
        <fade_when_player_occluded value="false" alphawhenoccluding="0.500000" alphawhennotoccluding="1.000000" />
        <texture filename="Media/levels/hot_spring/fog_bg.png" />
        <horizontalflip value="false" />
        <verticalflip value="true" />
        <isanimated value="false" />
        <foliage_sway_props bottom_left_intensity_x="0.000000" bottom_left_intensity_y="0.000000" bottom_right_intensity_x="0.000000" bottom_right_intensity_y="0.000000" top_left_intensity_x="0.000000" top_left_intensity_y="0.000000" top_right_intensity_x="0.000000" top_right_intensity_y="0.000000" time_multiplier="1.000000" />
    </Sprite>
    <Sprite id="39" level_edit_locked="false" updateable="true" always_update="false">
        <position depth_layer="kMiddleForeground" y="115.000000" x="-806.747803" rotation="0.019629" auto_rotate_value="0.000000" />
        <dimensions height="722.785034" width="362.640228" native="false" repeatX="false" repeatY="false" />
        <material value="grassground" />
        <sine_wave_props active="false" x_offset="0.000000" y_offset="0.000000" amplitude="0.000000" rand_init_step="0" />
        <pos_audio_props enabled="false" file="" dim_x="0.000000" dim_y="0.000000" fade_dim_x="0.000000" fade_dim_y="0.000000" play_delay="0.100000" repeat="false" />
        <alpha value="0.970000" />
        <effect name="effectlighttexture" noiseintensity="0.000000" wobbleintensity="0.000000" pixelwobbleintensity="0.000000" pixelwobblespeedmod="0.000000" />
        <fade_when_player_occluded value="false" alphawhenoccluding="0.500000" alphawhennotoccluding="1.000000" />
        <texture filename="Media/levels/hot_spring/stalagmite_close_2.png" />
        <horizontalflip value="false" />
        <verticalflip value="true" />
        <isanimated value="false" />
        <foliage_sway_props bottom_left_intensity_x="0.000000" bottom_left_intensity_y="0.000000" bottom_right_intensity_x="0.000000" bottom_right_intensity_y="0.000000" top_left_intensity_x="0.000000" top_left_intensity_y="0.000000" top_right_intensity_x="0.000000" top_right_intensity_y="0.000000" time_multiplier="1.000000" />
    </Sprite>
    <Sprite id="40" level_edit_locked="false" updateable="true" always_update="false">
        <position depth_layer="kNearForeground" y="-393.999939" x="863.952026" rotation="0.019629" auto_rotate_value="0.000000" />
        <dimensions height="487.926758" width="244.805542" native="false" repeatX="false" repeatY="false" />
        <material value="grassground" />
        <sine_wave_props active="false" x_offset="0.000000" y_offset="0.000000" amplitude="0.000000" rand_init_step="0" />
        <pos_audio_props enabled="false" file="" dim_x="0.000000" dim_y="0.000000" fade_dim_x="0.000000" fade_dim_y="0.000000" play_delay="0.100000" repeat="false" />
        <alpha value="0.900000" />
        <effect name="effectlighttexture" noiseintensity="0.000000" wobbleintensity="0.000000" pixelwobbleintensity="0.000000" pixelwobblespeedmod="0.000000" />
        <fade_when_player_occluded value="false" alphawhenoccluding="0.500000" alphawhennotoccluding="1.000000" />
        <texture filename="Media/levels/hot_spring/stalagmite_close.png" />
        <horizontalflip value="false" />
        <verticalflip value="false" />
        <isanimated value="false" />
        <foliage_sway_props bottom_left_intensity_x="0.000000" bottom_left_intensity_y="0.000000" bottom_right_intensity_x="0.000000" bottom_right_intensity_y="0.000000" top_left_intensity_x="0.000000" top_left_intensity_y="0.000000" top_right_intensity_x="0.000000" top_right_intensity_y="0.000000" time_multiplier="1.000000" />
    </Sprite>
    <AudioObject id="41" level_edit_locked="false" updateable="true" always_update="true">
        <position depth_layer="kGround" y="-80.000000" x="1285.451904" rotation="0.000000" auto_rotate_value="0.000000" />
        <dimensions height="500.000000" width="1000.000000" />
        <material value="" />
        <sine_wave_props active="false" x_offset="0.000000" y_offset="0.000000" amplitude="0.000000" rand_init_step="0" />
        <pos_audio_props enabled="false" file="" dim_x="0.000000" dim_y="0.000000" fade_dim_x="0.000000" fade_dim_y="0.000000" play_delay="0.100000" repeat="false" />
        <audiofile value="Ambient\water_cave.wav" />
        <adjustvolumetocamera value="true" />
        <repeat value="true" />
        <fadedimensions x="3000.000000" y="3000.000000" />
    </AudioObject>
    <AudioObject id="42" level_edit_locked="false" updateable="true" always_update="true">
        <position depth_layer="kGround" y="4.000000" x="-792.548096" rotation="0.000000" auto_rotate_value="0.000000" />
        <dimensions height="500.000000" width="500.000000" />
        <material value="" />
        <sine_wave_props active="false" x_offset="0.000000" y_offset="0.000000" amplitude="0.000000" rand_init_step="0" />
        <pos_audio_props enabled="false" file="" dim_x="0.000000" dim_y="0.000000" fade_dim_x="0.000000" fade_dim_y="0.000000" play_delay="0.100000" repeat="false" />
        <audiofile value="Ambient\water_drip.wav" />
        <adjustvolumetocamera value="true" />
        <repeat value="true" />
        <fadedimensions x="1500.000000" y="3000.000000" />
    </AudioObject>
    <AudioObject id="43" level_edit_locked="false" updateable="true" always_update="true">
        <position depth_layer="kGround" y="-77.000000" x="618.451904" rotation="0.000000" auto_rotate_value="0.000000" />
        <dimensions height="500.000000" width="500.000000" />
        <material value="" />
        <sine_wave_props active="false" x_offset="0.000000" y_offset="0.000000" amplitude="0.000000" rand_init_step="0" />
        <pos_audio_props enabled="false" file="" dim_x="0.000000" dim_y="0.000000" fade_dim_x="0.000000" fade_dim_y="0.000000" play_delay="0.100000" repeat="false" />
        <audiofile value="Ambient\water_drip.wav" />
        <adjustvolumetocamera value="true" />
        <repeat value="true" />
        <fadedimensions x="1500.000000" y="3000.000000" />
    </AudioObject>
    <AudioObject id="44" level_edit_locked="false" updateable="true" always_update="true">
        <position depth_layer="kGround" y="-5.000000" x="-322.548096" rotation="0.000000" auto_rotate_value="0.000000" />
        <dimensions height="500.000000" width="300.000000" />
        <material value="" />
        <sine_wave_props active="false" x_offset="0.000000" y_offset="0.000000" amplitude="0.000000" rand_init_step="0" />
        <pos_audio_props enabled="false" file="" dim_x="0.000000" dim_y="0.000000" fade_dim_x="0.000000" fade_dim_y="0.000000" play_delay="0.100000" repeat="false" />
        <audiofile value="Ambient\water_drip_2.mp3" />
        <adjustvolumetocamera value="true" />
        <repeat value="true" />
        <fadedimensions x="900.000000" y="3000.000000" />
    </AudioObject>
    <AudioObject id="45" level_edit_locked="false" updateable="true" always_update="true">
        <position depth_layer="kGround" y="2.000000" x="-975.548096" rotation="0.000000" auto_rotate_value="0.000000" />
        <dimensions height="500.000000" width="1000.000000" />
        <material value="" />
        <sine_wave_props active="false" x_offset="0.000000" y_offset="0.000000" amplitude="0.000000" rand_init_step="0" />
        <pos_audio_props enabled="false" file="" dim_x="0.000000" dim_y="0.000000" fade_dim_x="0.000000" fade_dim_y="0.000000" play_delay="0.100000" repeat="false" />
        <audiofile value="Ambient\water_cave.wav" />
        <adjustvolumetocamera value="true" />
        <repeat value="true" />
        <fadedimensions x="3000.000000" y="3000.000000" />
    </AudioObject>
    <ParticleSpray id="46" level_edit_locked="false" updateable="true" always_update="false">
        <position depth_layer="kGroundBack" y="1006.000000" x="59.451904" rotation="0.000000" auto_rotate_value="0.000000" spawn_spread_x="100.000000" spawn_spread_y="5.000000" />
        <dimensions height="3000.000000" width="400.000000" />
        <material value="" />
        <sine_wave_props active="false" x_offset="0.000000" y_offset="0.000000" amplitude="0.000000" rand_init_step="0" />
        <pos_audio_props enabled="false" file="" dim_x="0.000000" dim_y="0.000000" fade_dim_x="0.000000" fade_dim_y="0.000000" play_delay="0.100000" repeat="false" />
        <alpha value="1.000000" />
        <effect name="effectlighttexture" />
        <fade_when_player_occluded value="false" alphawhenoccluding="0.500000" alphawhennotoccluding="1.000000" />
        <numparticles value="20.000000" />
        <texture filename="Media\levels\hot_spring\water_drip.png" />
        <direction x="0.000000" y="-1.000000" />
        <spread value="1.000000" />
        <speed min="12.000000" max="20.000000" />
        <livetime min="2.500000" max="10.000000" />
        <size min="16.000000" max="28.000000" scaleto="true" scaletovalue="1.100000" />
        <gravity value="0.000000" />
        <loop value="true" looptime="0.000000" />
        <brightness min="1.000000" max="1.000000" />
        <fade_time_percent out="0.500000" in="0.100000" />
    </ParticleSpray>
    <Sprite id="47" level_edit_locked="false" updateable="true" always_update="false">
        <position depth_layer="kGround" y="-337.194305" x="56.451904" rotation="0.170269" auto_rotate_value="0.000000" />
        <dimensions height="413.000000" width="2152.163330" native="false" repeatX="true" repeatY="false" />
        <material value="grassground" />
        <sine_wave_props active="false" x_offset="0.000000" y_offset="0.000000" amplitude="0.000000" rand_init_step="0" />
        <pos_audio_props enabled="false" file="" dim_x="0.000000" dim_y="0.000000" fade_dim_x="0.000000" fade_dim_y="0.000000" play_delay="0.100000" repeat="false" />
        <alpha value="1.000000" />
        <effect name="effectpixelwobble" noiseintensity="0.000000" wobbleintensity="0.000000" pixelwobbleintensity="0.001500" pixelwobblespeedmod="8.000000" />
        <fade_when_player_occluded value="false" alphawhenoccluding="0.500000" alphawhennotoccluding="1.000000" />
        <texture filename="Media/levels/hot_spring/cave_floor_4.png" />
        <horizontalflip value="false" />
        <verticalflip value="true" />
        <isanimated value="false" />
        <foliage_sway_props bottom_left_intensity_x="0.000000" bottom_left_intensity_y="0.000000" bottom_right_intensity_x="0.000000" bottom_right_intensity_y="0.000000" top_left_intensity_x="0.000000" top_left_intensity_y="0.000000" top_right_intensity_x="0.000000" top_right_intensity_y="0.000000" time_multiplier="1.000000" />
    </Sprite>
    <Sprite id="48" level_edit_locked="false" updateable="true" always_update="false">
        <position depth_layer="kGround" y="-325.999939" x="-3093.043701" rotation="0.220300" auto_rotate_value="0.000000" />
        <dimensions height="1090.308960" width="5406.665039" native="false" repeatX="false" repeatY="false" />
        <material value="grassground" />
        <sine_wave_props active="false" x_offset="0.000000" y_offset="0.000000" amplitude="0.000000" rand_init_step="0" />
        <pos_audio_props enabled="false" file="" dim_x="0.000000" dim_y="0.000000" fade_dim_x="0.000000" fade_dim_y="0.000000" play_delay="0.100000" repeat="false" />
        <alpha value="1.000000" />
        <effect name="effectlighttexture" noiseintensity="0.000000" wobbleintensity="0.000000" pixelwobbleintensity="0.000000" pixelwobblespeedmod="0.000000" />
        <fade_when_player_occluded value="false" alphawhenoccluding="0.500000" alphawhennotoccluding="1.000000" />
        <texture filename="Media/levels/hot_spring/cave_floor_3.png" />
        <horizontalflip value="true" />
        <verticalflip value="false" />
        <isanimated value="false" />
        <foliage_sway_props bottom_left_intensity_x="0.000000" bottom_left_intensity_y="0.000000" bottom_right_intensity_x="0.000000" bottom_right_intensity_y="0.000000" top_left_intensity_x="0.000000" top_left_intensity_y="0.000000" top_right_intensity_x="0.000000" top_right_intensity_y="0.000000" time_multiplier="1.000000" />
    </Sprite>
    <ParticleSpray id="49" level_edit_locked="false" updateable="true" always_update="false">
        <position depth_layer="kFarForeground" y="-395.300262" x="-870.848267" rotation="0.000000" auto_rotate_value="0.000000" spawn_spread_x="70.000000" spawn_spread_y="10.000000" />
        <dimensions height="317.648529" width="982.725159" />
        <material value="" />
        <sine_wave_props active="false" x_offset="0.000000" y_offset="0.000000" amplitude="0.000000" rand_init_step="0" />
        <pos_audio_props enabled="false" file="" dim_x="0.000000" dim_y="0.000000" fade_dim_x="0.000000" fade_dim_y="0.000000" play_delay="0.100000" repeat="false" />
        <alpha value="1.000000" />
        <effect name="effectlighttexture" />
        <fade_when_player_occluded value="false" alphawhenoccluding="0.500000" alphawhennotoccluding="1.000000" />
        <numparticles value="100.000000" />
        <texture filename="Media\levels\hot_spring\fog_2.png" />
        <direction x="0.000000" y="1.000000" />
        <spread value="1.000000" />
        <speed min="0.050000" max="0.150000" />
        <livetime min="4.000000" max="6.500000" />
        <size min="50.000000" max="100.000000" scaleto="true" scaletovalue="10.000000" />
        <gravity value="0.000000" />
        <loop value="true" looptime="0.000000" />
        <brightness min="1.000000" max="1.000000" />
        <fade_time_percent out="0.250000" in="0.250000" />
    </ParticleSpray>
    <ParticleSpray id="50" level_edit_locked="false" updateable="true" always_update="false">
        <position depth_layer="kFarForeground" y="-229.000000" x="812.451904" rotation="0.000000" auto_rotate_value="0.000000" spawn_spread_x="40.000000" spawn_spread_y="20.000000" />
        <dimensions height="317.648529" width="982.725159" />
        <material value="" />
        <sine_wave_props active="false" x_offset="0.000000" y_offset="0.000000" amplitude="0.000000" rand_init_step="0" />
        <pos_audio_props enabled="false" file="" dim_x="0.000000" dim_y="0.000000" fade_dim_x="0.000000" fade_dim_y="0.000000" play_delay="0.100000" repeat="false" />
        <alpha value="1.000000" />
        <effect name="effectlighttexture" />
        <fade_when_player_occluded value="false" alphawhenoccluding="0.500000" alphawhennotoccluding="1.000000" />
        <numparticles value="30.000000" />
        <texture filename="Media\levels\hot_spring\fog_2.png" />
        <direction x="0.000000" y="1.000000" />
        <spread value="1.000000" />
        <speed min="0.050000" max="0.150000" />
        <livetime min="4.000000" max="6.500000" />
        <size min="50.000000" max="100.000000" scaleto="true" scaletovalue="20.000000" />
        <gravity value="0.000000" />
        <loop value="true" looptime="0.000000" />
        <brightness min="1.000000" max="1.000000" />
        <fade_time_percent out="0.250000" in="0.250000" />
    </ParticleSpray>
    <Sprite id="51" level_edit_locked="false" updateable="true" always_update="false">
        <position depth_layer="kGround" y="-116.000046" x="-887.648071" rotation="0.260202" auto_rotate_value="0.000000" />
        <dimensions height="413.000000" width="2152.163330" native="false" repeatX="true" repeatY="false" />
        <material value="grassground" />
        <sine_wave_props active="false" x_offset="0.000000" y_offset="0.000000" amplitude="0.000000" rand_init_step="0" />
        <pos_audio_props enabled="false" file="" dim_x="0.000000" dim_y="0.000000" fade_dim_x="0.000000" fade_dim_y="0.000000" play_delay="0.100000" repeat="false" />
        <alpha value="1.000000" />
        <effect name="effectlighttexture" noiseintensity="0.000000" wobbleintensity="0.000000" pixelwobbleintensity="0.000000" pixelwobblespeedmod="0.000000" />
        <fade_when_player_occluded value="false" alphawhenoccluding="0.500000" alphawhennotoccluding="1.000000" />
        <texture filename="Media/levels/hot_spring/cave_floor_3.png" />
        <horizontalflip value="false" />
        <verticalflip value="true" />
        <isanimated value="false" />
        <foliage_sway_props bottom_left_intensity_x="0.000000" bottom_left_intensity_y="0.000000" bottom_right_intensity_x="0.000000" bottom_right_intensity_y="0.000000" top_left_intensity_x="0.000000" top_left_intensity_y="0.000000" top_right_intensity_x="0.000000" top_right_intensity_y="0.000000" time_multiplier="1.000000" />
    </Sprite>
    <LevelTrigger id="52" level_edit_locked="false" updateable="true" always_update="true">
        <position depth_layer="kGround" y="44.000000" x="1926.451904" rotation="0.000000" auto_rotate_value="0.000000" />
        <dimensions height="4000.000000" width="1200.000000" />
        <material value="" />
        <sine_wave_props active="false" x_offset="0.000000" y_offset="0.000000" amplitude="0.000000" rand_init_step="0" />
        <pos_audio_props enabled="false" file="" dim_x="0.000000" dim_y="0.000000" fade_dim_x="0.000000" fade_dim_y="0.000000" play_delay="0.100000" repeat="false" />
        <level_to_load value="XmlFiles\levels\underwater_cave_4.xml" />
    </LevelTrigger>
    <SaveShrine id="53" level_edit_locked="false" updateable="true" always_update="true">
        <position depth_layer="kGroundFront" y="-280.000000" x="197.751862" rotation="0.000000" auto_rotate_value="0.000000" />
        <dimensions height="594.016724" width="792.024719" />
        <material value="" />
        <sine_wave_props active="false" x_offset="0.000000" y_offset="0.000000" amplitude="0.000000" rand_init_step="0" />
        <pos_audio_props enabled="false" file="" dim_x="0.000000" dim_y="0.000000" fade_dim_x="0.000000" fade_dim_y="0.000000" play_delay="0.100000" repeat="false" />
    </SaveShrine>
    <LevelEntry id="54" level_edit_locked="false" updateable="true" always_update="true">
        <position depth_layer="kGround" y="-80.000000" x="1038.451904" rotation="0.000000" auto_rotate_value="0.000000" />
        <dimensions height="250.000000" width="250.000000" />
        <material value="" />
        <sine_wave_props active="false" x_offset="0.000000" y_offset="0.000000" amplitude="0.000000" rand_init_step="0" />
        <pos_audio_props enabled="false" file="" dim_x="0.000000" dim_y="0.000000" fade_dim_x="0.000000" fade_dim_y="0.000000" play_delay="0.100000" repeat="false" />
        <level_came_from value="XmlFiles\levels\underwater_cave_4.xml" />
        <player_direction x="-1.000000" />
        <door_id value="" />
    </LevelEntry>
</level>
